mne_kit_gui/__init__.py
mne_kit_gui/_backend.py
mne_kit_gui/_fiducials_gui.py
mne_kit_gui/_file_traits.py
mne_kit_gui/_help.py
mne_kit_gui/_kit2fiff_gui.py
mne_kit_gui/_marker_gui.py
mne_kit_gui/_utils.py
mne_kit_gui/_viewer.py
mne_kit_gui/conftest.py
mne_kit_gui/help/kit2fiff.json
mne_kit_gui/tests/__init__.py
mne_kit_gui/tests/test_fiducials_gui.py
mne_kit_gui/tests/test_file_traits.py
mne_kit_gui/tests/test_kit2fiff_gui.py
mne_kit_gui/tests/test_marker_gui.py
mne_kit_gui-1.3.0.dist-info/LICENSE
mne_kit_gui-1.3.0.dist-info/METADATA
mne_kit_gui-1.3.0.dist-info/WHEEL
mne_kit_gui-1.3.0.dist-info/top_level.txt
mne_kit_gui-1.3.0.dist-info/RECORD
